unidecode/__init__.py
unidecode/__main__.py
unidecode/py.typed
unidecode/util.py
unidecode/x000.py
unidecode/x001.py
unidecode/x002.py
unidecode/x003.py
unidecode/x004.py
unidecode/x005.py
unidecode/x006.py
unidecode/x007.py
unidecode/x009.py
unidecode/x00a.py
unidecode/x00b.py
unidecode/x00c.py
unidecode/x00d.py
unidecode/x00e.py
unidecode/x00f.py
unidecode/x010.py
unidecode/x011.py
unidecode/x012.py
unidecode/x013.py
unidecode/x014.py
unidecode/x015.py
unidecode/x016.py
unidecode/x017.py
unidecode/x018.py
unidecode/x01d.py
unidecode/x01e.py
unidecode/x01f.py
unidecode/x020.py
unidecode/x021.py
unidecode/x022.py
unidecode/x023.py
unidecode/x024.py
unidecode/x025.py
unidecode/x026.py
unidecode/x027.py
unidecode/x028.py
unidecode/x029.py
unidecode/x02a.py
unidecode/x02c.py
unidecode/x02e.py
unidecode/x02f.py
unidecode/x030.py
unidecode/x031.py
unidecode/x032.py
unidecode/x033.py
unidecode/x04d.py
unidecode/x04e.py
unidecode/x04f.py
unidecode/x050.py
unidecode/x051.py
unidecode/x052.py
unidecode/x053.py
unidecode/x054.py
unidecode/x055.py
unidecode/x056.py
unidecode/x057.py
unidecode/x058.py
unidecode/x059.py
unidecode/x05a.py
unidecode/x05b.py
unidecode/x05c.py
unidecode/x05d.py
unidecode/x05e.py
unidecode/x05f.py
unidecode/x060.py
unidecode/x061.py
unidecode/x062.py
unidecode/x063.py
unidecode/x064.py
unidecode/x065.py
unidecode/x066.py
unidecode/x067.py
unidecode/x068.py
unidecode/x069.py
unidecode/x06a.py
unidecode/x06b.py
unidecode/x06c.py
unidecode/x06d.py
unidecode/x06e.py
unidecode/x06f.py
unidecode/x070.py
unidecode/x071.py
unidecode/x072.py
unidecode/x073.py
unidecode/x074.py
unidecode/x075.py
unidecode/x076.py
unidecode/x077.py
unidecode/x078.py
unidecode/x079.py
unidecode/x07a.py
unidecode/x07b.py
unidecode/x07c.py
unidecode/x07d.py
unidecode/x07e.py
unidecode/x07f.py
unidecode/x080.py
unidecode/x081.py
unidecode/x082.py
unidecode/x083.py
unidecode/x084.py
unidecode/x085.py
unidecode/x086.py
unidecode/x087.py
unidecode/x088.py
unidecode/x089.py
Unidecode-1.3.8.dist-info/LICENSE
Unidecode-1.3.8.dist-info/METADATA
Unidecode-1.3.8.dist-info/WHEEL
Unidecode-1.3.8.dist-info/entry_points.txt
Unidecode-1.3.8.dist-info/top_level.txt
Unidecode-1.3.8.dist-info/RECORD
